ebookshelf/__init__.py
ebookshelf/__main__.py
ebookshelf/book.py
ebookshelf/case.py
ebookshelf/ebookshelf.py
ebookshelf/library.py
ebookshelf/shelf.py
ebookshelf-0.1.0.dist-info/LICENSE-APACHE
ebookshelf-0.1.0.dist-info/LICENSE-MIT
ebookshelf-0.1.0.dist-info/METADATA
ebookshelf-0.1.0.dist-info/WHEEL
ebookshelf-0.1.0.dist-info/entry_points.txt
ebookshelf-0.1.0.dist-info/top_level.txt
ebookshelf-0.1.0.dist-info/RECORD
