Metadata-Version: 2.1
Name: ebookshelf
Version: 0.1.0
Summary: UNKNOWN
Home-page: https://codeberg.org/dr.ops/ebookshelf
Author: Andy Drop
Author-email: andy@plaindrops.de
Maintainer: Andy Drop
Maintainer-email: andy@plaindrops.de
License: MIT/Apache-2.0
Platform: UNKNOWN
Classifier: Development Status :: 4 - Beta
Classifier: Intended Audience :: Developers
Classifier: License :: OSI Approved :: MIT License
Classifier: License :: OSI Approved :: Apache Software License
Classifier: Natural Language :: English
Classifier: Operating System :: OS Independent
Classifier: Programming Language :: Python :: 2.7
Classifier: Programming Language :: Python :: 3.5
Classifier: Programming Language :: Python :: 3.6
Classifier: Programming Language :: Python :: Implementation :: CPython
Classifier: Programming Language :: Python :: Implementation :: PyPy
